[
    {
        "+name": "ReflectionProbe",
        "+trs": {
            "pos": {
                "x": 0.0,
                "y": 0.0,
                "z": 0.0
            },
            "rot": {
                "x": 0.0,
                "y": -0.0,
                "z": 0.0
            },
            "scale": {
                "x": 1.0,
                "y": 1.0,
                "z": 0.9999985694885254
            }
        },
        "+type": "ReflectionProbe",
        "ambientTerm": {
            "x": 0.0,
            "y": 0.0,
            "z": 0.30000001192092896
        },
        "environmentMap": "gen-data/skyb",
        "environmentMap_importHint_": "engine-data/default-skybox/skyb.env",
        "~children": []
    },
    {
        "+name": "Light 1",
        "+trs": {
            "pos": {
                "x": 17.54451560974121,
                "y": 22.3966064453125,
                "z": 74.69779968261719
            },
            "rot": {
                "x": -26.886985778808594,
                "y": -50.029232025146484,
                "z": 0.015337168239057064
            },
            "scale": {
                "x": 0.9999054074287415,
                "y": 0.9999671578407288,
                "z": 1.0000194311141968
            }
        },
        "+type": "SpotLight",
        "color": {
            "x": 0.9082745909690857,
            "y": 0.9715302586555481,
            "z": 0.788287878036499
        },
        "contantTerm": 1.0,
        "far": 100.0,
        "hasShadow": true,
        "innerAperture": 2.094395160675049,
        "intensity": 1.0,
        "linearTerm": 0.0,
        "maxShadowBias": 0.004999999888241291,
        "near": 0.8999999761581421,
        "outerAperture": 2.094395160675049,
        "quadraticTerm": 0.0,
        "samples": 4,
        "shadowMapHeight": 2048,
        "shadowMapWidth": 2048,
        "~children": []
    },
    {
        "+name": "MetalRoughSpheres",
        "+trs": {
            "pos": {
                "x": -18.83384895324707,
                "y": 16.74765396118164,
                "z": 5.980527877807617
            },
            "rot": {
                "x": -172.24755859375,
                "y": 8.039215087890625,
                "z": 179.99818420410156
            },
            "scale": {
                "x": 0.7999998331069946,
                "y": 0.800000011920929,
                "z": 0.7999995946884155
            }
        },
        "+type": "Geometry",
        "model": "gen-data/MetalRoughSpheres",
        "model_importHint_": "gltf-samples/2.0/MetalRoughSpheres/glTF/MetalRoughSpheres.gltf",
        "~children": []
    },
    {
        "+name": "Sea",
        "+trs": {
            "pos": {
                "x": 0.0,
                "y": 1.3733479976654053,
                "z": 0.0
            },
            "rot": {
                "x": 0.0,
                "y": -0.0,
                "z": 0.0
            },
            "scale": {
                "x": 1.0,
                "y": 1.0,
                "z": 1.0
            }
        },
        "+type": "Geometry",
        "model": "gen-data/_TERRAIN_/mesh_1",
        "model_importHint_": "",
        "~children": []
    },
    {
        "+name": "Terrain",
        "+trs": {
            "pos": {
                "x": 0.0,
                "y": 0.0,
                "z": 0.0
            },
            "rot": {
                "x": 0.0,
                "y": -0.0,
                "z": 0.0
            },
            "scale": {
                "x": 1.0,
                "y": 1.0,
                "z": 1.0
            }
        },
        "+type": "Geometry",
        "model": "gen-data/_TERRAIN_/mesh",
        "model_importHint_": "",
        "~children": []
    },
    {
        "+name": "TerrainWalkerUser_new",
        "+trs": {
            "pos": {
                "x": 15.596713066101074,
                "y": 8.300677299499512,
                "z": 40.413177490234375
            },
            "rot": {
                "x": -20.186094284057617,
                "y": -31.33856773376465,
                "z": -0.0016803400358185172
            },
            "scale": {
                "x": 0.9992472529411316,
                "y": 0.9998353123664856,
                "z": 0.9995030164718628
            }
        },
        "+type": "TerrainWalkerUser",
        "gravity": -9.899999618530273,
        "heightMultiplier": 8.020000457763672,
        "heightmap": "gen-data/_TERRAIN_/height3_sq_4300",
        "heightmap_importHint_": "_terrain_/height3_sq_4300.png",
        "jumpVelocity": 10.0,
        "movementSpeed": 1.0,
        "playerHeight": 0.3100000023841858,
        "terrainWorldScale": 100.0,
        "turningSpeed": 0.4000000059604645,
        "~children": [
            {
                "+name": "DefaultCamLocation",
                "+trs": {
                    "pos": {
                        "x": 0.0013580322265625,
                        "y": 0.0013229846954345703,
                        "z": -0.0005779266357421875
                    },
                    "rot": {
                        "x": 9.903545287670568e-05,
                        "y": -0.0011542430147528648,
                        "z": 0.0035933498293161392
                    },
                    "scale": {
                        "x": 1.0000511407852173,
                        "y": 1.000023365020752,
                        "z": 1.0000407695770264
                    }
                },
                "+type": "WindowCamera",
                "far": 1000.0,
                "focalLength": 1.0,
                "hFov": 1.890677809715271,
                "hFovOffset": 0.0,
                "near": 0.029999999329447746,
                "vFov": 1.2566370964050293,
                "vFovOffset": 0.0,
                "~children": [
                    {
                        "+name": "Transform_new",
                        "+trs": {
                            "pos": {
                                "x": 0.0007228851900435984,
                                "y": -0.00016593934560660273,
                                "z": -5.722046353184851e-06
                            },
                            "rot": {
                                "x": 0.00032363340142183006,
                                "y": -0.00041087859426625073,
                                "z": 9.338150448456872e-06
                            },
                            "scale": {
                                "x": 0.10000000149011612,
                                "y": 0.10000006854534149,
                                "z": 0.10000000149011612
                            }
                        },
                        "+type": "Transform",
                        "~children": [
                            {
                                "+name": "Geometry_new_Copy",
                                "+trs": {
                                    "pos": {
                                        "x": -0.535369873046875,
                                        "y": -0.23408126831054688,
                                        "z": -0.615020751953125
                                    },
                                    "rot": {
                                        "x": 0.0005038330564275384,
                                        "y": 17.599916458129883,
                                        "z": -0.0011235552374273539
                                    },
                                    "scale": {
                                        "x": 1.0004884004592896,
                                        "y": 1.0003511905670166,
                                        "z": 1.0005429983139038
                                    }
                                },
                                "+type": "Geometry",
                                "model": "gen-data/Gun/Gun",
                                "model_importHint_": "../../../../../Downloads/Cerberus_by_Andrew_Maximov/gltf-export/untitled.gltf",
                                "~children": []
                            },
                            {
                                "+name": "Geometry_new",
                                "+trs": {
                                    "pos": {
                                        "x": 0.498077392578125,
                                        "y": -0.256622314453125,
                                        "z": -0.5688629150390625
                                    },
                                    "rot": {
                                        "x": 0.0002654474519658834,
                                        "y": -19.800996780395508,
                                        "z": -0.0001839110191212967
                                    },
                                    "scale": {
                                        "x": 1.0003776550292969,
                                        "y": 1.0002599954605103,
                                        "z": 1.0005327463150024
                                    }
                                },
                                "+type": "Geometry",
                                "model": "gen-data/Gun/Gun",
                                "model_importHint_": "../../../../../Downloads/Cerberus_by_Andrew_Maximov/gltf-export/untitled.gltf",
                                "~children": []
                            }
                        ]
                    }
                ]
            }
        ]
    }
]